eic_utils/__init__.py
eic_utils/base.py
eic_utils/cache.py
eic_utils/database.py
eic_utils/image.py
eic_utils/samples.py
eic_utils/spider.py
eic_utils-3.2.dist-info/METADATA
eic_utils-3.2.dist-info/WHEEL
eic_utils-3.2.dist-info/top_level.txt
eic_utils-3.2.dist-info/RECORD
