Metadata-Version: 2.1
Name: eic-utils
Version: 3.2
Summary: basic utils for python3
Home-page: http://github.com/indestinee/utils
Author: indestinee
Author-email: indestinee@gmail.com
License: UNKNOWN
Platform: UNKNOWN
Classifier: Programming Language :: Python :: 3
Classifier: License :: OSI Approved :: MIT License
